{
  "information": {
    "name": "Rafael Sousa",
    "photo": "https://avatars.githubusercontent.com/u/43481051?v=4",
    "job": "Desenvolvedor ",
    "location": "São Paulo - SP",
    "phone": "(11) 96070-2307",
    "email": "rafael.p.sousa@hotmail.com",
    "github": "RafaaSousa"
  },
    "skills": {
      "hardSkills": [
        {
          "name": "HTML",
          "logo": "https://raw.githubusercontent.com/RafaaSousa/portfolio/master/assets/img/icons/html.svg"
        },
        {
          "name": "CSS",
          "logo": "https://raw.githubusercontent.com/RafaaSousa/portfolio/master/assets/img/icons/css.svg"
        },
        {
          "name": "JavaScript",
          "logo": "https://raw.githubusercontent.com/RafaaSousa/portfolio/master/assets/img/icons/javascript.svg"
        },
        {
          "name": "React",
          "logo": "https://raw.githubusercontent.com/RafaaSousa/portfolio/master/assets/img/icons/react.svg"
        },
        {
          "name": "Node.js",
          "logo": "https://raw.githubusercontent.com/RafaaSousa/portfolio/master/assets/img/icons/nodejs.svg"
        },
        {
          "name": "Postgresql",
          "logo": "https://raw.githubusercontent.com/digitalinnovationone/js-developer-portfolio/main/data/imgs/postgresql.png"
        }
      ],
      "softSkills": [
        "Empatia",
        "Liderança",
        "Trabalho em equipe",
        "Flexibilidade",
        "Organização"
      ]
    },
    "languages": [
      "Português BR",
      "Inglês (intermediário)"
    ],
    "portfolio": [
      {
        "name": "Notes App - Crie suas notas usando a voz",
        "url": "https://github.com/RafaaSousa/nlw-expert-notes",
        "github": true
      },
      {
        "name": "Calculadora - Faça calculos de maneira simples",
        "url": "https://github.com/RafaaSousa/Calculadora",
        "github": true
      },
      {
        "name": "Weather App - Descubra quantos graus está na sua cidade",
        "url": "https://github.com/RafaaSousa/weather-app",
        "github": true
      },
      {
        "name": "Buscador de CEP - Buscar o CEP da sua rua ficou mais fácil",
        "url": "https://github.com/RafaaSousa/buscador",
        "github": true
      },
      {
        "name": "Portfólio - Crie seu próprio portfólio usando esse projeto como base",
        "url": "https://github.com/RafaaSousa/portfolio",
        "github": true
      }
    ],
    "professionalExperience": [
      {
        "name": "###########",
        "period": "########",
        "description": "######"
      }    
    ]
  }
